{
    "total": [
        {
            "id": "100005399974808",
            "count": 2
        },
        {
            "id": "100010295341625",
            "count": 0
        },
        {
            "id": "100048975223261",
            "count": 0
        },
        {
            "id": "100010872618953",
            "count": 0
        },
        {
            "id": "100010851456335",
            "count": 134
        },
        {
            "id": "100000376441471",
            "count": 3
        },
        {
            "id": "100024680241094",
            "count": 33
        },
        {
            "id": "100008519718621",
            "count": 0
        },
        {
            "id": "100007828906989",
            "count": 4
        },
        {
            "id": "100025965308353",
            "count": 337
        },
        {
            "id": "100001098455658",
            "count": 547
        },
        {
            "id": "100031133040032",
            "count": 28
        },
        {
            "id": "100038141927576",
            "count": 5
        },
        {
            "id": "100053513322881",
            "count": 19
        },
        {
            "id": "100027669353138",
            "count": 0
        },
        {
            "id": "100055755865162",
            "count": 0
        },
        {
            "id": "100017983382767",
            "count": 20
        },
        {
            "id": "100036231517888",
            "count": 157
        },
        {
            "id": "100048816348048",
            "count": 41
        },
        {
            "id": "100078714226384",
            "count": 0
        },
        {
            "id": "100004112948229",
            "count": 1
        },
        {
            "id": "100088154556576",
            "count": 586
        },
        {
            "id": "100027266034157",
            "count": 10
        },
        {
            "id": "100089855538797",
            "count": 660
        },
        {
            "id": "100021900640152",
            "count": 0
        },
        {
            "id": "100007023435812",
            "count": 0
        },
        {
            "id": "100010074694749",
            "count": 32
        },
        {
            "id": "100010343984032",
            "count": 0
        },
        {
            "id": "100030593837339",
            "count": 0
        },
        {
            "id": "100030127763775",
            "count": 0
        },
        {
            "id": "100034086345546",
            "count": 0
        },
        {
            "id": "100040164439697",
            "count": 5
        },
        {
            "id": "100022367776188",
            "count": 22
        },
        {
            "id": "100008745676374",
            "count": 0
        },
        {
            "id": "100077691835671",
            "count": 0
        },
        {
            "id": "100056381440220",
            "count": 210
        },
        {
            "id": "100044648675640",
            "count": 0
        },
        {
            "id": "100005071237632",
            "count": 0
        },
        {
            "id": "100074010341361",
            "count": 14
        },
        {
            "id": "100025697650899",
            "count": 0
        },
        {
            "id": "100056376864986",
            "count": 0
        },
        {
            "id": "100008203004097",
            "count": 2
        },
        {
            "id": "100051560712743",
            "count": 5
        },
        {
            "id": "100034658161598",
            "count": 75
        },
        {
            "id": "100009492519807",
            "count": 1
        },
        {
            "id": "100080742369075",
            "count": 234
        },
        {
            "id": "100090006483826",
            "count": 0
        },
        {
            "id": "100090936052047",
            "count": 0
        },
        {
            "id": "100065181827875",
            "count": 0
        },
        {
            "id": "100052380679382",
            "count": 0
        },
        {
            "id": "100073731191766",
            "count": 0
        },
        {
            "id": "100084495626712",
            "count": 0
        },
        {
            "id": "100077313395792",
            "count": 2196
        },
        {
            "id": "100034233130232",
            "count": 0
        },
        {
            "id": "100041623599528",
            "count": 8
        },
        {
            "id": "100051694850870",
            "count": 0
        },
        {
            "id": "100039628178101",
            "count": 0
        },
        {
            "id": "100073660227322",
            "count": 8
        },
        {
            "id": "100009167177495",
            "count": 40
        },
        {
            "id": "100025466683106",
            "count": 0
        },
        {
            "id": "100077070300551",
            "count": 8
        },
        {
            "id": "100007359612039",
            "count": 13
        },
        {
            "id": "100034383213099",
            "count": 0
        },
        {
            "id": "100014540290454",
            "count": 0
        },
        {
            "id": "100048561292978",
            "count": 644
        },
        {
            "id": "100031566042722",
            "count": 256
        },
        {
            "id": "100014830098397",
            "count": 38
        },
        {
            "id": "100015473404117",
            "count": 0
        },
        {
            "id": "100040551379448",
            "count": 0
        },
        {
            "id": "100057378228327",
            "count": 30
        },
        {
            "id": "100010294295881",
            "count": 116
        },
        {
            "id": "100069463914769",
            "count": 67
        },
        {
            "id": "100063260620465",
            "count": 62
        },
        {
            "id": "100043601286252",
            "count": 0
        },
        {
            "id": "100044191598642",
            "count": 11
        },
        {
            "id": "100015054305521",
            "count": 179
        },
        {
            "id": "100052419605370",
            "count": 1211
        },
        {
            "id": "100041219531906",
            "count": 2
        },
        {
            "id": "100089124229991",
            "count": 11
        },
        {
            "id": "100018064162732",
            "count": 131
        },
        {
            "id": "100013705600597",
            "count": 488
        },
        {
            "id": "100090572663819",
            "count": 0
        },
        {
            "id": "100026450419902",
            "count": 0
        },
        {
            "id": "100034837787551",
            "count": 6
        },
        {
            "id": "100009461997276",
            "count": 12
        },
        {
            "id": "100048432905426",
            "count": 0
        },
        {
            "id": "100067122755501",
            "count": 27
        },
        {
            "id": "100074753293482",
            "count": 36
        },
        {
            "id": "100078786724982",
            "count": 2
        },
        {
            "id": "100079196630165",
            "count": 974
        },
        {
            "id": "100013815225154",
            "count": 2
        },
        {
            "id": "100089488084535",
            "count": 13
        },
        {
            "id": "100053483708297",
            "count": 1728
        },
        {
            "id": "100058486843373",
            "count": 0
        },
        {
            "id": "100069400449963",
            "count": 58
        },
        {
            "id": "100055632586900",
            "count": 1639
        },
        {
            "id": "100085149474363",
            "count": 14
        },
        {
            "id": "100042797796681",
            "count": 0
        },
        {
            "id": "100066014461303",
            "count": 2488
        },
        {
            "id": "100061314142011",
            "count": 27
        },
        {
            "id": "100015582406225",
            "count": 135
        },
        {
            "id": "100084390475850",
            "count": 11
        },
        {
            "id": "100026107429011",
            "count": 0
        },
        {
            "id": "100015326372925",
            "count": 256
        },
        {
            "id": "100027370416302",
            "count": 1
        },
        {
            "id": "100073925087201",
            "count": 14
        },
        {
            "id": "100037711232386",
            "count": 1743
        },
        {
            "id": "100047213045916",
            "count": 1
        },
        {
            "id": "100040224006883",
            "count": 47
        },
        {
            "id": "100015077025240",
            "count": 94
        },
        {
            "id": "100027056261626",
            "count": 0
        },
        {
            "id": "100007158796596",
            "count": 34
        },
        {
            "id": "100064217914106",
            "count": 121
        },
        {
            "id": "100091363366578",
            "count": 1
        },
        {
            "id": "100073204690500",
            "count": 0
        },
        {
            "id": "100050956162561",
            "count": 49
        },
        {
            "id": "100047887366084",
            "count": 61
        },
        {
            "id": "100024300976662",
            "count": 0
        },
        {
            "id": "100071636576099",
            "count": 9
        },
        {
            "id": "100041668570533",
            "count": 1073
        },
        {
            "id": "100051807037752",
            "count": 0
        },
        {
            "id": "100008059066610",
            "count": 18
        },
        {
            "id": "100053395998035",
            "count": 48
        },
        {
            "id": "61551446518489",
            "count": 0
        },
        {
            "id": "100073512553764",
            "count": 0
        },
        {
            "id": "100035973543807",
            "count": 1
        },
        {
            "id": "100091344458469",
            "count": 618
        },
        {
            "id": "100027952612936",
            "count": 99
        },
        {
            "id": "100078216607891",
            "count": 2
        },
        {
            "id": "100017336831405",
            "count": 0
        },
        {
            "id": "100016591539468",
            "count": 369
        },
        {
            "id": "100094469166856",
            "count": 2437
        },
        {
            "id": "100044501018946",
            "count": 2
        },
        {
            "id": "100056259933554",
            "count": 4
        },
        {
            "id": "100014343060086",
            "count": 77
        },
        {
            "id": "100077193343212",
            "count": 175
        },
        {
            "id": "100053779121174",
            "count": 75
        },
        {
            "id": "100027039516065",
            "count": 385
        },
        {
            "id": "100064901298185",
            "count": 474
        },
        {
            "id": "100064573285150",
            "count": 292
        },
        {
            "id": "100047504554005",
            "count": 1205
        },
        {
            "id": "100054638868722",
            "count": 41
        },
        {
            "id": "100041990565923",
            "count": 1027
        },
        {
            "id": "61550226386641",
            "count": 1075
        },
        {
            "id": "100051786424251",
            "count": 40
        },
        {
            "id": "100023128592547",
            "count": 151
        },
        {
            "id": "100006474958727",
            "count": 4
        },
        {
            "id": "61552015658303",
            "count": 434
        },
        {
            "id": "100036921758223",
            "count": 14
        },
        {
            "id": "100089699576670",
            "count": 24
        },
        {
            "id": "100031003510300",
            "count": 48
        },
        {
            "id": "100038490645044",
            "count": 44
        },
        {
            "id": "100045760656023",
            "count": 1122
        },
        {
            "id": "100006360090592",
            "count": 14
        },
        {
            "id": "100054130774624",
            "count": 21
        },
        {
            "id": "100080716627589",
            "count": 41
        },
        {
            "id": "100081040767318",
            "count": 36
        },
        {
            "id": "100015636996669",
            "count": 14
        },
        {
            "id": "100047808826017",
            "count": 5
        },
        {
            "id": "100072164630652",
            "count": 2
        },
        {
            "id": "100060569773923",
            "count": 46
        }
    ],
    "week": [
        {
            "id": "100005399974808",
            "count": 0,
            "name": "Quốc Cường"
        },
        {
            "id": "100010295341625",
            "count": 0,
            "name": "Thái Hoàng Vũ"
        },
        {
            "id": "100048975223261",
            "count": 0,
            "name": "Nguyễn Kiệt"
        },
        {
            "id": "100010872618953",
            "count": 0,
            "name": "Tú Phan"
        },
        {
            "id": "100010851456335",
            "count": 0,
            "name": "Nguyễn Văn Khá"
        },
        {
            "id": "100000376441471",
            "count": 0,
            "name": "Lynk Vjt"
        },
        {
            "id": "100024680241094",
            "count": 0,
            "name": "Nguyễn Quang Thịnh"
        },
        {
            "id": "100008519718621",
            "count": 0,
            "name": "Thanh Phong"
        },
        {
            "id": "100007828906989",
            "count": 0,
            "name": "Nguyễn Hạnh Nguyên"
        },
        {
            "id": "100025965308353",
            "count": 0,
            "name": "Hồ Hoàng Quý"
        },
        {
            "id": "100001098455658",
            "count": 0,
            "name": "Nguyễn Như Quỳnh"
        },
        {
            "id": "100031133040032",
            "count": 0,
            "name": "Long Vũ"
        },
        {
            "id": "100038141927576",
            "count": 0,
            "name": "Nguyễn Anh Tuấn"
        },
        {
            "id": "100053513322881",
            "count": 0,
            "name": "Trần Thịnh"
        },
        {
            "id": "100027669353138",
            "count": 0,
            "name": "Tùng Louis"
        },
        {
            "id": "100055755865162",
            "count": 0,
            "name": "Hữu Ngọc"
        },
        {
            "id": "100017983382767",
            "count": 0,
            "name": "Đặng Nguyễn N.Thành"
        },
        {
            "id": "100036231517888",
            "count": 0,
            "name": "Trương Đức Tài"
        },
        {
            "id": "100048816348048",
            "count": 0,
            "name": "Sin Đi Cảnh"
        },
        {
            "id": "100078714226384",
            "count": 0,
            "name": "Hoàng Bear"
        },
        {
            "id": "100004112948229",
            "count": 0,
            "name": "Vương Sơn"
        },
        {
            "id": "100088154556576",
            "count": 0,
            "name": "Phan Huệ"
        },
        {
            "id": "100027266034157",
            "count": 0,
            "name": "Mi Mi"
        },
        {
            "id": "100089855538797",
            "count": 0,
            "name": "Bảo Đang Rảnh"
        },
        {
            "id": "100021900640152",
            "count": 0,
            "name": "Trang Nguyễn"
        },
        {
            "id": "100007023435812",
            "count": 0,
            "name": "Vĩnh Kỳ"
        },
        {
            "id": "100010074694749",
            "count": 0,
            "name": "Nguyễn Tuấn Huy"
        },
        {
            "id": "100010343984032",
            "count": 0,
            "name": "XuÂn Trường Nguyễn"
        },
        {
            "id": "100030593837339",
            "count": 0,
            "name": "Nguyễn Xuân Hoàng"
        },
        {
            "id": "100030127763775",
            "count": 0,
            "name": "Tuấn Danh"
        },
        {
            "id": "100034086345546",
            "count": 0,
            "name": "Nguyễn Bá Kiên"
        },
        {
            "id": "100040164439697",
            "count": 0,
            "name": "Hữu Trung"
        },
        {
            "id": "100022367776188",
            "count": 0,
            "name": "Tiến Chiển"
        },
        {
            "id": "100008745676374",
            "count": 0,
            "name": "Dương Tuấn Công"
        },
        {
            "id": "100077691835671",
            "count": 0,
            "name": "Chính"
        },
        {
            "id": "100056381440220",
            "count": 0,
            "name": "Thu Trang"
        },
        {
            "id": "100044648675640",
            "count": 0,
            "name": "Hoàng Tuấn"
        },
        {
            "id": "100005071237632",
            "count": 0,
            "name": "Nguyễn Hà"
        },
        {
            "id": "100074010341361",
            "count": 0,
            "name": "Long Trần"
        },
        {
            "id": "100025697650899",
            "count": 0,
            "name": "Thắng Black"
        },
        {
            "id": "100056376864986",
            "count": 0,
            "name": "Yến Nhi"
        },
        {
            "id": "100008203004097",
            "count": 0,
            "name": "Tạ Văn Thắng"
        },
        {
            "id": "100051560712743",
            "count": 0,
            "name": "Helen SaRa"
        },
        {
            "id": "100034658161598",
            "count": 0,
            "name": "Nguyễn Phi"
        },
        {
            "id": "100009492519807",
            "count": 0,
            "name": "Chu Anh Cương"
        },
        {
            "id": "100080742369075",
            "count": 0,
            "name": "Thuỳ Linh"
        },
        {
            "id": "100090006483826",
            "count": 0,
            "name": "On Leon"
        },
        {
            "id": "100090936052047",
            "count": 0,
            "name": "Tỷ Pon"
        },
        {
            "id": "100065181827875",
            "count": 0,
            "name": "Nguyên Mạc"
        },
        {
            "id": "100052380679382",
            "count": 0,
            "name": "Thành Nguyễn"
        },
        {
            "id": "100073731191766",
            "count": 0,
            "name": "ファム チュオン"
        },
        {
            "id": "100084495626712",
            "count": 0,
            "name": "Nguyễn Đức Trí Tuệ"
        },
        {
            "id": "100077313395792",
            "count": 0,
            "name": "Duy Minh"
        },
        {
            "id": "100034233130232",
            "count": 0,
            "name": "Văn Quân"
        },
        {
            "id": "100041623599528",
            "count": 0,
            "name": "Bé Thii"
        },
        {
            "id": "100051694850870",
            "count": 0,
            "name": "Gia Thien"
        },
        {
            "id": "100039628178101",
            "count": 0,
            "name": "Trương Nhân"
        },
        {
            "id": "100073660227322",
            "count": 0,
            "name": "Bé Cưng"
        },
        {
            "id": "100009167177495",
            "count": 0,
            "name": "Ngự Giáp Văn"
        },
        {
            "id": "100025466683106",
            "count": 0,
            "name": "Huynh Gia Phuc"
        },
        {
            "id": "100077070300551",
            "count": 0,
            "name": "Lê Văn Sử"
        },
        {
            "id": "100007359612039",
            "count": 0,
            "name": "Nguyễn Hữu Dân"
        },
        {
            "id": "100034383213099",
            "count": 0,
            "name": "Khánh Văn"
        },
        {
            "id": "100014540290454",
            "count": 0,
            "name": "Hiếu Huỳnh"
        },
        {
            "id": "100048561292978",
            "count": 0,
            "name": "Minh Tiến"
        },
        {
            "id": "100031566042722",
            "count": 0,
            "name": "Trần Văn Trường"
        },
        {
            "id": "100014830098397",
            "count": 0,
            "name": "Phạm Huy"
        },
        {
            "id": "100015473404117",
            "count": 0,
            "name": "NT Kim Thanh"
        },
        {
            "id": "100040551379448",
            "count": 0,
            "name": "Nguyen Duc Viet"
        },
        {
            "id": "100057378228327",
            "count": 0,
            "name": "Trần Cường"
        },
        {
            "id": "100010294295881",
            "count": 0,
            "name": "Việt Nguyễn"
        },
        {
            "id": "100069463914769",
            "count": 0,
            "name": "Hoàng Khang"
        },
        {
            "id": "100063260620465",
            "count": 0,
            "name": "Nhật Huy"
        },
        {
            "id": "100043601286252",
            "count": 0,
            "name": "Hoàng Anh Khoa"
        },
        {
            "id": "100044191598642",
            "count": 0,
            "name": "Nguyễn Đức Luân"
        },
        {
            "id": "100015054305521",
            "count": 0,
            "name": "Toàn Minh Đặng"
        },
        {
            "id": "100052419605370",
            "count": 0,
            "name": "Bach Văn Sao"
        },
        {
            "id": "100041219531906",
            "count": 0,
            "name": "Hoàng Đức Huy"
        },
        {
            "id": "100089124229991",
            "count": 0,
            "name": "Bình Văn Phong"
        },
        {
            "id": "100018064162732",
            "count": 0,
            "name": "Gia Bảo"
        },
        {
            "id": "100013705600597",
            "count": 0,
            "name": "Bảo Ân"
        },
        {
            "id": "100090572663819",
            "count": 0,
            "name": "Thiên Bình"
        },
        {
            "id": "100026450419902",
            "count": 0,
            "name": "Đoàn Văn Thùy"
        },
        {
            "id": "100034837787551",
            "count": 0,
            "name": "Thuỳ Trang"
        },
        {
            "id": "100009461997276",
            "count": 0,
            "name": "Nguyễn Văn Nam"
        },
        {
            "id": "100048432905426",
            "count": 0,
            "name": "Mạc Đức Duy"
        },
        {
            "id": "100067122755501",
            "count": 0,
            "name": "Trần Hữu Toàn"
        },
        {
            "id": "100074753293482",
            "count": 0,
            "name": "Đặng Hào Quang"
        },
        {
            "id": "100078786724982",
            "count": 0,
            "name": "Uyên Nguyên"
        },
        {
            "id": "100079196630165",
            "count": 0,
            "name": "Trần Thị Hằng"
        },
        {
            "id": "100013815225154",
            "count": 0,
            "name": "Văn Hậu"
        },
        {
            "id": "100089488084535",
            "count": 0,
            "name": "Đạt Blue 💎"
        },
        {
            "id": "100053483708297",
            "count": 0,
            "name": "Văn Lâm"
        },
        {
            "id": "100058486843373",
            "count": 0,
            "name": "Trần Thắng"
        },
        {
            "id": "100069400449963",
            "count": 0,
            "name": "PhẠm TiẾn"
        },
        {
            "id": "100055632586900",
            "count": 0,
            "name": "Nguyễn Văn Đại"
        },
        {
            "id": "100085149474363",
            "count": 0,
            "name": "Tũn Đang Đi Học"
        },
        {
            "id": "100042797796681",
            "count": 0,
            "name": "Tăng Cường"
        },
        {
            "id": "100066014461303",
            "count": 0,
            "name": "Đỗ Tú"
        },
        {
            "id": "100061314142011",
            "count": 0,
            "name": "Thiên Trường"
        },
        {
            "id": "100015582406225",
            "count": 0,
            "name": "Thu Hồng"
        },
        {
            "id": "100084390475850",
            "count": 0,
            "name": "Ngô Công Tuấn"
        },
        {
            "id": "100026107429011",
            "count": 0,
            "name": "Vương Quyết"
        },
        {
            "id": "100015326372925",
            "count": 0,
            "name": "Nguyễn Thị Hằng"
        },
        {
            "id": "100027370416302",
            "count": 0,
            "name": "Tạ Thanh Tùng"
        },
        {
            "id": "100073925087201",
            "count": 0,
            "name": "Nguyễn Trung"
        },
        {
            "id": "100037711232386",
            "count": 0,
            "name": "Cậu Nhóc"
        },
        {
            "id": "100047213045916",
            "count": 0,
            "name": "Thủy Bee"
        },
        {
            "id": "100040224006883",
            "count": 0,
            "name": "Lê Khắc Anh"
        },
        {
            "id": "100015077025240",
            "count": 0,
            "name": "Bùi Thị Diễm Quỳnh"
        },
        {
            "id": "100027056261626",
            "count": 0,
            "name": "Bích Huệ"
        },
        {
            "id": "100007158796596",
            "count": 0,
            "name": "Lê Ngọc Đức"
        },
        {
            "id": "100064217914106",
            "count": 0,
            "name": "Dâuu Sama"
        },
        {
            "id": "100091363366578",
            "count": 0,
            "name": "Hữu Huy"
        },
        {
            "id": "100073204690500",
            "count": 0,
            "name": "Minh Quân"
        },
        {
            "id": "100050956162561",
            "count": 0,
            "name": "Đăng Nam"
        },
        {
            "id": "100047887366084",
            "count": 0,
            "name": "Nguyễn Đình Minh Quy"
        },
        {
            "id": "100024300976662",
            "count": 0,
            "name": "Vu Minh Hai"
        },
        {
            "id": "100071636576099",
            "count": 0,
            "name": "Minh Quân"
        },
        {
            "id": "100041668570533",
            "count": 0,
            "name": "Minh Thuận"
        },
        {
            "id": "100051807037752",
            "count": 0,
            "name": "Nguyễn Ninh"
        },
        {
            "id": "100008059066610",
            "count": 0,
            "name": "Lê Thị Mỹ Linh"
        },
        {
            "id": "100053395998035",
            "count": 0,
            "name": "Minh Hiếu"
        },
        {
            "id": "61551446518489",
            "count": 0,
            "name": "Bé Gấu"
        },
        {
            "id": "100073512553764",
            "count": 0,
            "name": "Aley Anh Thư"
        },
        {
            "id": "100035973543807",
            "count": 0,
            "name": "Nguyễn Duy Toàn"
        },
        {
            "id": "100091344458469",
            "count": 0,
            "name": "Bùi Hữu Thịnh"
        },
        {
            "id": "100027952612936",
            "count": 0,
            "name": "Em Bé"
        },
        {
            "id": "100078216607891",
            "count": 0,
            "name": "Khánh Chi"
        },
        {
            "id": "100017336831405",
            "count": 0,
            "name": "Nguyễn Đức Hải"
        },
        {
            "id": "100016591539468",
            "count": 0,
            "name": "Nguyễn Huy Hoàng"
        },
        {
            "id": "100094469166856",
            "count": 0,
            "name": "Mai Tân Tiến"
        },
        {
            "id": "100044501018946",
            "count": 0,
            "name": "Khánh Nè"
        },
        {
            "id": "100056259933554",
            "count": 0,
            "name": "Pé Pi"
        },
        {
            "id": "100014343060086",
            "count": 0,
            "name": "Thắng Trịnh"
        },
        {
            "id": "100077193343212",
            "count": 0,
            "name": "Mlem Kem"
        },
        {
            "id": "100053779121174",
            "count": 0,
            "name": "Peony Anh"
        },
        {
            "id": "100027039516065",
            "count": 0,
            "name": "Meii Meii"
        },
        {
            "id": "100064901298185",
            "count": 0,
            "name": "Vũ Đình Hảo"
        },
        {
            "id": "100064573285150",
            "count": 0,
            "name": "Nhung Bùi"
        },
        {
            "id": "100047504554005",
            "count": 0,
            "name": "Thu Uyên"
        },
        {
            "id": "100054638868722",
            "count": 0,
            "name": "Hoàng Văn Thái"
        },
        {
            "id": "100041990565923",
            "count": 0,
            "name": "Nguyễn Quốc Bình"
        },
        {
            "id": "61550226386641",
            "count": 0,
            "name": "Huyen Mai"
        },
        {
            "id": "100051786424251",
            "count": 0,
            "name": "Đ.V Quyến"
        },
        {
            "id": "100023128592547",
            "count": 0,
            "name": "Trần Khanh"
        },
        {
            "id": "100006474958727",
            "count": 0,
            "name": "Phạm Tâm Long"
        },
        {
            "id": "61552015658303",
            "count": 0,
            "name": "Nguyễn Hoàng Ánh"
        },
        {
            "id": "100036921758223",
            "count": 0,
            "name": "Huỳnh Ngọc Thoa"
        },
        {
            "id": "100089699576670",
            "count": 0,
            "name": "Tong Khoi Nguyen"
        },
        {
            "id": "100031003510300",
            "count": 0,
            "name": "Tien Anh Nguyễn"
        },
        {
            "id": "100038490645044",
            "count": 0,
            "name": "Trang Đài"
        },
        {
            "id": "100045760656023",
            "count": 0,
            "name": "Đỗ Thanh Thảo"
        },
        {
            "id": "100006360090592",
            "count": 0,
            "name": "Nguyễn Thanh Huyền"
        },
        {
            "id": "100054130774624",
            "count": 0,
            "name": "Nhiên Lê"
        },
        {
            "id": "100080716627589",
            "count": 0,
            "name": "Diễm Quỳnh"
        },
        {
            "id": "100081040767318",
            "count": 0,
            "name": "Mỹ Đình"
        },
        {
            "id": "100015636996669",
            "count": 0,
            "name": "Cậu Út"
        },
        {
            "id": "100047808826017",
            "count": 0,
            "name": "Minh Khai"
        },
        {
            "id": "100072164630652",
            "count": 0,
            "name": "Bảo Nhyy"
        },
        {
            "id": "100060569773923",
            "count": 0,
            "name": "Tú Nguyên"
        }
    ],
    "day": [
        {
            "id": "100005399974808",
            "count": 0,
            "name": "Quốc Cường"
        },
        {
            "id": "100010295341625",
            "count": 0,
            "name": "Thái Hoàng Vũ"
        },
        {
            "id": "100048975223261",
            "count": 0,
            "name": "Nguyễn Kiệt"
        },
        {
            "id": "100010872618953",
            "count": 0,
            "name": "Tú Phan"
        },
        {
            "id": "100010851456335",
            "count": 0,
            "name": "Nguyễn Văn Khá"
        },
        {
            "id": "100000376441471",
            "count": 0,
            "name": "Lynk Vjt"
        },
        {
            "id": "100024680241094",
            "count": 0,
            "name": "Nguyễn Quang Thịnh"
        },
        {
            "id": "100008519718621",
            "count": 0,
            "name": "Thanh Phong"
        },
        {
            "id": "100007828906989",
            "count": 0,
            "name": "Nguyễn Hạnh Nguyên"
        },
        {
            "id": "100025965308353",
            "count": 0,
            "name": "Hồ Hoàng Quý"
        },
        {
            "id": "100001098455658",
            "count": 0,
            "name": "Nguyễn Như Quỳnh"
        },
        {
            "id": "100031133040032",
            "count": 0,
            "name": "Long Vũ"
        },
        {
            "id": "100038141927576",
            "count": 0,
            "name": "Nguyễn Anh Tuấn"
        },
        {
            "id": "100053513322881",
            "count": 0,
            "name": "Trần Thịnh"
        },
        {
            "id": "100027669353138",
            "count": 0,
            "name": "Tùng Louis"
        },
        {
            "id": "100055755865162",
            "count": 0,
            "name": "Hữu Ngọc"
        },
        {
            "id": "100017983382767",
            "count": 0,
            "name": "Đặng Nguyễn N.Thành"
        },
        {
            "id": "100036231517888",
            "count": 0,
            "name": "Trương Đức Tài"
        },
        {
            "id": "100048816348048",
            "count": 0,
            "name": "Sin Đi Cảnh"
        },
        {
            "id": "100078714226384",
            "count": 0,
            "name": "Hoàng Bear"
        },
        {
            "id": "100004112948229",
            "count": 0,
            "name": "Vương Sơn"
        },
        {
            "id": "100088154556576",
            "count": 0,
            "name": "Phan Huệ"
        },
        {
            "id": "100027266034157",
            "count": 0,
            "name": "Mi Mi"
        },
        {
            "id": "100089855538797",
            "count": 0,
            "name": "Bảo Đang Rảnh"
        },
        {
            "id": "100021900640152",
            "count": 0,
            "name": "Trang Nguyễn"
        },
        {
            "id": "100007023435812",
            "count": 0,
            "name": "Vĩnh Kỳ"
        },
        {
            "id": "100010074694749",
            "count": 0,
            "name": "Nguyễn Tuấn Huy"
        },
        {
            "id": "100010343984032",
            "count": 0,
            "name": "XuÂn Trường Nguyễn"
        },
        {
            "id": "100030593837339",
            "count": 0,
            "name": "Nguyễn Xuân Hoàng"
        },
        {
            "id": "100030127763775",
            "count": 0,
            "name": "Tuấn Danh"
        },
        {
            "id": "100034086345546",
            "count": 0,
            "name": "Nguyễn Bá Kiên"
        },
        {
            "id": "100040164439697",
            "count": 0,
            "name": "Hữu Trung"
        },
        {
            "id": "100022367776188",
            "count": 0,
            "name": "Tiến Chiển"
        },
        {
            "id": "100008745676374",
            "count": 0,
            "name": "Dương Tuấn Công"
        },
        {
            "id": "100077691835671",
            "count": 0,
            "name": "Chính"
        },
        {
            "id": "100056381440220",
            "count": 0,
            "name": "Thu Trang"
        },
        {
            "id": "100044648675640",
            "count": 0,
            "name": "Hoàng Tuấn"
        },
        {
            "id": "100005071237632",
            "count": 0,
            "name": "Nguyễn Hà"
        },
        {
            "id": "100074010341361",
            "count": 0,
            "name": "Long Trần"
        },
        {
            "id": "100025697650899",
            "count": 0,
            "name": "Thắng Black"
        },
        {
            "id": "100056376864986",
            "count": 0,
            "name": "Yến Nhi"
        },
        {
            "id": "100008203004097",
            "count": 0,
            "name": "Tạ Văn Thắng"
        },
        {
            "id": "100051560712743",
            "count": 0,
            "name": "Helen SaRa"
        },
        {
            "id": "100034658161598",
            "count": 0,
            "name": "Nguyễn Phi"
        },
        {
            "id": "100009492519807",
            "count": 0,
            "name": "Chu Anh Cương"
        },
        {
            "id": "100080742369075",
            "count": 0,
            "name": "Thuỳ Linh"
        },
        {
            "id": "100090006483826",
            "count": 0,
            "name": "On Leon"
        },
        {
            "id": "100090936052047",
            "count": 0,
            "name": "Tỷ Pon"
        },
        {
            "id": "100065181827875",
            "count": 0,
            "name": "Nguyên Mạc"
        },
        {
            "id": "100052380679382",
            "count": 0,
            "name": "Thành Nguyễn"
        },
        {
            "id": "100073731191766",
            "count": 0,
            "name": "ファム チュオン"
        },
        {
            "id": "100084495626712",
            "count": 0,
            "name": "Nguyễn Đức Trí Tuệ"
        },
        {
            "id": "100077313395792",
            "count": 0,
            "name": "Duy Minh"
        },
        {
            "id": "100034233130232",
            "count": 0,
            "name": "Văn Quân"
        },
        {
            "id": "100041623599528",
            "count": 0,
            "name": "Bé Thii"
        },
        {
            "id": "100051694850870",
            "count": 0,
            "name": "Gia Thien"
        },
        {
            "id": "100039628178101",
            "count": 0,
            "name": "Trương Nhân"
        },
        {
            "id": "100073660227322",
            "count": 0,
            "name": "Bé Cưng"
        },
        {
            "id": "100009167177495",
            "count": 0,
            "name": "Ngự Giáp Văn"
        },
        {
            "id": "100025466683106",
            "count": 0,
            "name": "Huynh Gia Phuc"
        },
        {
            "id": "100077070300551",
            "count": 0,
            "name": "Lê Văn Sử"
        },
        {
            "id": "100007359612039",
            "count": 0,
            "name": "Nguyễn Hữu Dân"
        },
        {
            "id": "100034383213099",
            "count": 0,
            "name": "Khánh Văn"
        },
        {
            "id": "100014540290454",
            "count": 0,
            "name": "Hiếu Huỳnh"
        },
        {
            "id": "100048561292978",
            "count": 0,
            "name": "Minh Tiến"
        },
        {
            "id": "100031566042722",
            "count": 0,
            "name": "Trần Văn Trường"
        },
        {
            "id": "100014830098397",
            "count": 0,
            "name": "Phạm Huy"
        },
        {
            "id": "100015473404117",
            "count": 0,
            "name": "NT Kim Thanh"
        },
        {
            "id": "100040551379448",
            "count": 0,
            "name": "Nguyen Duc Viet"
        },
        {
            "id": "100057378228327",
            "count": 0,
            "name": "Trần Cường"
        },
        {
            "id": "100010294295881",
            "count": 0,
            "name": "Việt Nguyễn"
        },
        {
            "id": "100069463914769",
            "count": 0,
            "name": "Hoàng Khang"
        },
        {
            "id": "100063260620465",
            "count": 0,
            "name": "Nhật Huy"
        },
        {
            "id": "100043601286252",
            "count": 0,
            "name": "Hoàng Anh Khoa"
        },
        {
            "id": "100044191598642",
            "count": 0,
            "name": "Nguyễn Đức Luân"
        },
        {
            "id": "100015054305521",
            "count": 0,
            "name": "Toàn Minh Đặng"
        },
        {
            "id": "100052419605370",
            "count": 0,
            "name": "Bach Văn Sao"
        },
        {
            "id": "100041219531906",
            "count": 0,
            "name": "Hoàng Đức Huy"
        },
        {
            "id": "100089124229991",
            "count": 0,
            "name": "Bình Văn Phong"
        },
        {
            "id": "100018064162732",
            "count": 0,
            "name": "Gia Bảo"
        },
        {
            "id": "100013705600597",
            "count": 0,
            "name": "Bảo Ân"
        },
        {
            "id": "100090572663819",
            "count": 0,
            "name": "Thiên Bình"
        },
        {
            "id": "100026450419902",
            "count": 0,
            "name": "Đoàn Văn Thùy"
        },
        {
            "id": "100034837787551",
            "count": 0,
            "name": "Thuỳ Trang"
        },
        {
            "id": "100009461997276",
            "count": 0,
            "name": "Nguyễn Văn Nam"
        },
        {
            "id": "100048432905426",
            "count": 0,
            "name": "Mạc Đức Duy"
        },
        {
            "id": "100067122755501",
            "count": 0,
            "name": "Trần Hữu Toàn"
        },
        {
            "id": "100074753293482",
            "count": 0,
            "name": "Đặng Hào Quang"
        },
        {
            "id": "100078786724982",
            "count": 0,
            "name": "Uyên Nguyên"
        },
        {
            "id": "100079196630165",
            "count": 0,
            "name": "Trần Thị Hằng"
        },
        {
            "id": "100013815225154",
            "count": 0,
            "name": "Văn Hậu"
        },
        {
            "id": "100089488084535",
            "count": 0,
            "name": "Đạt Blue 💎"
        },
        {
            "id": "100053483708297",
            "count": 0,
            "name": "Văn Lâm"
        },
        {
            "id": "100058486843373",
            "count": 0,
            "name": "Trần Thắng"
        },
        {
            "id": "100069400449963",
            "count": 0,
            "name": "PhẠm TiẾn"
        },
        {
            "id": "100055632586900",
            "count": 0,
            "name": "Nguyễn Văn Đại"
        },
        {
            "id": "100085149474363",
            "count": 0,
            "name": "Tũn Đang Đi Học"
        },
        {
            "id": "100042797796681",
            "count": 0,
            "name": "Tăng Cường"
        },
        {
            "id": "100066014461303",
            "count": 0,
            "name": "Đỗ Tú"
        },
        {
            "id": "100061314142011",
            "count": 0,
            "name": "Thiên Trường"
        },
        {
            "id": "100015582406225",
            "count": 0,
            "name": "Thu Hồng"
        },
        {
            "id": "100084390475850",
            "count": 0,
            "name": "Ngô Công Tuấn"
        },
        {
            "id": "100026107429011",
            "count": 0,
            "name": "Vương Quyết"
        },
        {
            "id": "100015326372925",
            "count": 0,
            "name": "Nguyễn Thị Hằng"
        },
        {
            "id": "100027370416302",
            "count": 0,
            "name": "Tạ Thanh Tùng"
        },
        {
            "id": "100073925087201",
            "count": 0,
            "name": "Nguyễn Trung"
        },
        {
            "id": "100037711232386",
            "count": 0,
            "name": "Cậu Nhóc"
        },
        {
            "id": "100047213045916",
            "count": 0,
            "name": "Thủy Bee"
        },
        {
            "id": "100040224006883",
            "count": 0,
            "name": "Lê Khắc Anh"
        },
        {
            "id": "100015077025240",
            "count": 0,
            "name": "Bùi Thị Diễm Quỳnh"
        },
        {
            "id": "100027056261626",
            "count": 0,
            "name": "Bích Huệ"
        },
        {
            "id": "100007158796596",
            "count": 0,
            "name": "Lê Ngọc Đức"
        },
        {
            "id": "100064217914106",
            "count": 0,
            "name": "Dâuu Sama"
        },
        {
            "id": "100091363366578",
            "count": 0,
            "name": "Hữu Huy"
        },
        {
            "id": "100073204690500",
            "count": 0,
            "name": "Minh Quân"
        },
        {
            "id": "100050956162561",
            "count": 0,
            "name": "Đăng Nam"
        },
        {
            "id": "100047887366084",
            "count": 0,
            "name": "Nguyễn Đình Minh Quy"
        },
        {
            "id": "100024300976662",
            "count": 0,
            "name": "Vu Minh Hai"
        },
        {
            "id": "100071636576099",
            "count": 0,
            "name": "Minh Quân"
        },
        {
            "id": "100041668570533",
            "count": 0,
            "name": "Minh Thuận"
        },
        {
            "id": "100051807037752",
            "count": 0,
            "name": "Nguyễn Ninh"
        },
        {
            "id": "100008059066610",
            "count": 0,
            "name": "Lê Thị Mỹ Linh"
        },
        {
            "id": "100053395998035",
            "count": 0,
            "name": "Minh Hiếu"
        },
        {
            "id": "61551446518489",
            "count": 0,
            "name": "Bé Gấu"
        },
        {
            "id": "100073512553764",
            "count": 0,
            "name": "Aley Anh Thư"
        },
        {
            "id": "100035973543807",
            "count": 0,
            "name": "Nguyễn Duy Toàn"
        },
        {
            "id": "100091344458469",
            "count": 0,
            "name": "Bùi Hữu Thịnh"
        },
        {
            "id": "100027952612936",
            "count": 0,
            "name": "Em Bé"
        },
        {
            "id": "100078216607891",
            "count": 0,
            "name": "Khánh Chi"
        },
        {
            "id": "100017336831405",
            "count": 0,
            "name": "Nguyễn Đức Hải"
        },
        {
            "id": "100016591539468",
            "count": 0,
            "name": "Nguyễn Huy Hoàng"
        },
        {
            "id": "100094469166856",
            "count": 0,
            "name": "Mai Tân Tiến"
        },
        {
            "id": "100044501018946",
            "count": 0,
            "name": "Khánh Nè"
        },
        {
            "id": "100056259933554",
            "count": 0,
            "name": "Pé Pi"
        },
        {
            "id": "100014343060086",
            "count": 0,
            "name": "Thắng Trịnh"
        },
        {
            "id": "100077193343212",
            "count": 0,
            "name": "Mlem Kem"
        },
        {
            "id": "100053779121174",
            "count": 0,
            "name": "Peony Anh"
        },
        {
            "id": "100027039516065",
            "count": 0,
            "name": "Meii Meii"
        },
        {
            "id": "100064901298185",
            "count": 0,
            "name": "Vũ Đình Hảo"
        },
        {
            "id": "100064573285150",
            "count": 0,
            "name": "Nhung Bùi"
        },
        {
            "id": "100047504554005",
            "count": 0,
            "name": "Thu Uyên"
        },
        {
            "id": "100054638868722",
            "count": 0,
            "name": "Hoàng Văn Thái"
        },
        {
            "id": "100041990565923",
            "count": 0,
            "name": "Nguyễn Quốc Bình"
        },
        {
            "id": "61550226386641",
            "count": 0,
            "name": "Huyen Mai"
        },
        {
            "id": "100051786424251",
            "count": 0,
            "name": "Đ.V Quyến"
        },
        {
            "id": "100023128592547",
            "count": 0,
            "name": "Trần Khanh"
        },
        {
            "id": "100006474958727",
            "count": 0,
            "name": "Phạm Tâm Long"
        },
        {
            "id": "61552015658303",
            "count": 0,
            "name": "Nguyễn Hoàng Ánh"
        },
        {
            "id": "100036921758223",
            "count": 0,
            "name": "Huỳnh Ngọc Thoa"
        },
        {
            "id": "100089699576670",
            "count": 0,
            "name": "Tong Khoi Nguyen"
        },
        {
            "id": "100031003510300",
            "count": 0,
            "name": "Tien Anh Nguyễn"
        },
        {
            "id": "100038490645044",
            "count": 0,
            "name": "Trang Đài"
        },
        {
            "id": "100045760656023",
            "count": 0,
            "name": "Đỗ Thanh Thảo"
        },
        {
            "id": "100006360090592",
            "count": 0,
            "name": "Nguyễn Thanh Huyền"
        },
        {
            "id": "100054130774624",
            "count": 0,
            "name": "Nhiên Lê"
        },
        {
            "id": "100080716627589",
            "count": 0,
            "name": "Diễm Quỳnh"
        },
        {
            "id": "100081040767318",
            "count": 0,
            "name": "Mỹ Đình"
        },
        {
            "id": "100015636996669",
            "count": 0,
            "name": "Cậu Út"
        },
        {
            "id": "100047808826017",
            "count": 0,
            "name": "Minh Khai"
        },
        {
            "id": "100072164630652",
            "count": 0,
            "name": "Bảo Nhyy"
        },
        {
            "id": "100060569773923",
            "count": 0,
            "name": "Tú Nguyên"
        }
    ],
    "time": 5,
    "last": {
        "time": 5,
        "day": [
            {
                "id": "100005399974808",
                "count": 0
            },
            {
                "id": "100010295341625",
                "count": 0
            },
            {
                "id": "100048975223261",
                "count": 0
            },
            {
                "id": "100010872618953",
                "count": 0
            },
            {
                "id": "100057840206964",
                "count": 0
            },
            {
                "id": "100010851456335",
                "count": 0
            },
            {
                "id": "100000376441471",
                "count": 0
            },
            {
                "id": "100024680241094",
                "count": 0
            },
            {
                "id": "100008519718621",
                "count": 0
            },
            {
                "id": "100007828906989",
                "count": 0
            },
            {
                "id": "100025965308353",
                "count": 0
            },
            {
                "id": "100001098455658",
                "count": 0
            },
            {
                "id": "100031133040032",
                "count": 0
            },
            {
                "id": "100038141927576",
                "count": 0
            },
            {
                "id": "100053513322881",
                "count": 0
            },
            {
                "id": "100027669353138",
                "count": 0
            },
            {
                "id": "100055755865162",
                "count": 0
            },
            {
                "id": "100017983382767",
                "count": 0
            },
            {
                "id": "100036231517888",
                "count": 0
            },
            {
                "id": "100046802320850",
                "count": 0
            },
            {
                "id": "100048816348048",
                "count": 0
            },
            {
                "id": "100078714226384",
                "count": 0
            },
            {
                "id": "100004112948229",
                "count": 0
            },
            {
                "id": "100088154556576",
                "count": 0
            },
            {
                "id": "100027266034157",
                "count": 0
            },
            {
                "id": "100089855538797",
                "count": 0
            },
            {
                "id": "100021900640152",
                "count": 0
            },
            {
                "id": "100007023435812",
                "count": 0
            },
            {
                "id": "100010074694749",
                "count": 0
            },
            {
                "id": "100010343984032",
                "count": 0
            },
            {
                "id": "100030593837339",
                "count": 0
            },
            {
                "id": "100030127763775",
                "count": 0
            },
            {
                "id": "100034086345546",
                "count": 0
            },
            {
                "id": "100040164439697",
                "count": 0
            },
            {
                "id": "100022367776188",
                "count": 0
            },
            {
                "id": "100008745676374",
                "count": 0
            },
            {
                "id": "100077691835671",
                "count": 0
            },
            {
                "id": "100056381440220",
                "count": 0
            },
            {
                "id": "100044648675640",
                "count": 0
            },
            {
                "id": "100057313594162",
                "count": 0
            },
            {
                "id": "100005071237632",
                "count": 0
            },
            {
                "id": "100074010341361",
                "count": 0
            },
            {
                "id": "100025697650899",
                "count": 0
            },
            {
                "id": "100056376864986",
                "count": 0
            },
            {
                "id": "100008203004097",
                "count": 0
            },
            {
                "id": "100051560712743",
                "count": 0
            },
            {
                "id": "100034658161598",
                "count": 0
            },
            {
                "id": "100009492519807",
                "count": 0
            },
            {
                "id": "100080742369075",
                "count": 0
            },
            {
                "id": "100090006483826",
                "count": 0
            },
            {
                "id": "100090936052047",
                "count": 0
            },
            {
                "id": "100065181827875",
                "count": 0
            },
            {
                "id": "100052380679382",
                "count": 0
            },
            {
                "id": "100073731191766",
                "count": 0
            },
            {
                "id": "100084495626712",
                "count": 0
            },
            {
                "id": "100077313395792",
                "count": 0
            },
            {
                "id": "100034233130232",
                "count": 0
            },
            {
                "id": "100041623599528",
                "count": 0
            },
            {
                "id": "100051694850870",
                "count": 0
            },
            {
                "id": "100039628178101",
                "count": 0
            },
            {
                "id": "100073660227322",
                "count": 0
            },
            {
                "id": "100009167177495",
                "count": 0
            },
            {
                "id": "100025466683106",
                "count": 0
            },
            {
                "id": "100077070300551",
                "count": 0
            },
            {
                "id": "100007359612039",
                "count": 0
            },
            {
                "id": "100034383213099",
                "count": 0
            },
            {
                "id": "100014540290454",
                "count": 0
            },
            {
                "id": "100048561292978",
                "count": 0
            },
            {
                "id": "100031566042722",
                "count": 0
            },
            {
                "id": "100014830098397",
                "count": 0
            },
            {
                "id": "100015473404117",
                "count": 0
            },
            {
                "id": "100040551379448",
                "count": 0
            },
            {
                "id": "100057378228327",
                "count": 0
            },
            {
                "id": "100010294295881",
                "count": 0
            },
            {
                "id": "100069463914769",
                "count": 0
            },
            {
                "id": "100063260620465",
                "count": 0
            },
            {
                "id": "100043601286252",
                "count": 0
            },
            {
                "id": "100044191598642",
                "count": 0
            },
            {
                "id": "100015054305521",
                "count": 0
            },
            {
                "id": "100052419605370",
                "count": 0
            },
            {
                "id": "100041219531906",
                "count": 0
            },
            {
                "id": "100089124229991",
                "count": 0
            },
            {
                "id": "100018064162732",
                "count": 0
            },
            {
                "id": "100013705600597",
                "count": 0
            },
            {
                "id": "100090572663819",
                "count": 0
            },
            {
                "id": "100026450419902",
                "count": 0
            },
            {
                "id": "100034837787551",
                "count": 0
            },
            {
                "id": "100009461997276",
                "count": 0
            },
            {
                "id": "100048432905426",
                "count": 0
            },
            {
                "id": "100067122755501",
                "count": 0
            },
            {
                "id": "100074753293482",
                "count": 0
            },
            {
                "id": "100078786724982",
                "count": 0
            },
            {
                "id": "100079196630165",
                "count": 0
            },
            {
                "id": "100013815225154",
                "count": 0
            },
            {
                "id": "100089488084535",
                "count": 0
            },
            {
                "id": "100053483708297",
                "count": 0
            },
            {
                "id": "100058486843373",
                "count": 0
            },
            {
                "id": "100069400449963",
                "count": 0
            },
            {
                "id": "100055632586900",
                "count": 0
            },
            {
                "id": "100085149474363",
                "count": 0
            },
            {
                "id": "100087707807880",
                "count": 0
            },
            {
                "id": "100042797796681",
                "count": 0
            },
            {
                "id": "100066014461303",
                "count": 0
            },
            {
                "id": "100061314142011",
                "count": 0
            },
            {
                "id": "100015582406225",
                "count": 0
            },
            {
                "id": "100084390475850",
                "count": 0
            },
            {
                "id": "100026107429011",
                "count": 0
            },
            {
                "id": "100015326372925",
                "count": 0
            },
            {
                "id": "100027370416302",
                "count": 0
            },
            {
                "id": "100073925087201",
                "count": 0
            },
            {
                "id": "100037711232386",
                "count": 0
            },
            {
                "id": "100047213045916",
                "count": 0
            },
            {
                "id": "100040224006883",
                "count": 0
            },
            {
                "id": "100015077025240",
                "count": 0
            },
            {
                "id": "100027056261626",
                "count": 0
            },
            {
                "id": "100007158796596",
                "count": 0
            },
            {
                "id": "100064217914106",
                "count": 0
            },
            {
                "id": "100091363366578",
                "count": 0
            },
            {
                "id": "100073204690500",
                "count": 0
            },
            {
                "id": "100008788001367",
                "count": 0
            },
            {
                "id": "100050956162561",
                "count": 0
            },
            {
                "id": "100071393430394",
                "count": 0
            },
            {
                "id": "100047887366084",
                "count": 0
            },
            {
                "id": "100024300976662",
                "count": 0
            },
            {
                "id": "100071636576099",
                "count": 0
            },
            {
                "id": "100041668570533",
                "count": 0
            },
            {
                "id": "100017620472036",
                "count": 0
            },
            {
                "id": "100051807037752",
                "count": 0
            },
            {
                "id": "100008059066610",
                "count": 0
            },
            {
                "id": "100053395998035",
                "count": 0
            },
            {
                "id": "61551446518489",
                "count": 0
            },
            {
                "id": "100073512553764",
                "count": 0
            },
            {
                "id": "100035973543807",
                "count": 0
            },
            {
                "id": "100091344458469",
                "count": 0
            },
            {
                "id": "100085486856463",
                "count": 0
            },
            {
                "id": "100027952612936",
                "count": 0
            },
            {
                "id": "100078216607891",
                "count": 0
            },
            {
                "id": "100017336831405",
                "count": 0
            },
            {
                "id": "100016591539468",
                "count": 0
            },
            {
                "id": "100094469166856",
                "count": 0
            },
            {
                "id": "100044501018946",
                "count": 0
            },
            {
                "id": "100056259933554",
                "count": 0
            },
            {
                "id": "100014343060086",
                "count": 0
            },
            {
                "id": "100077193343212",
                "count": 0
            },
            {
                "id": "100053779121174",
                "count": 0
            },
            {
                "id": "100048884326910",
                "count": 0
            },
            {
                "id": "100027039516065",
                "count": 0
            },
            {
                "id": "100064901298185",
                "count": 0
            },
            {
                "id": "100064573285150",
                "count": 0
            },
            {
                "id": "100047504554005",
                "count": 0
            },
            {
                "id": "100026957449851",
                "count": 0
            },
            {
                "id": "100047221725996",
                "count": 0
            },
            {
                "id": "100054638868722",
                "count": 0
            },
            {
                "id": "100041990565923",
                "count": 0
            },
            {
                "id": "61550226386641",
                "count": 0
            },
            {
                "id": "61551799898681",
                "count": 0
            },
            {
                "id": "100051786424251",
                "count": 0
            },
            {
                "id": "100023128592547",
                "count": 0
            },
            {
                "id": "100006474958727",
                "count": 0
            },
            {
                "id": "61552015658303",
                "count": 0
            },
            {
                "id": "100036921758223",
                "count": 0
            },
            {
                "id": "100089699576670",
                "count": 0
            },
            {
                "id": "100031003510300",
                "count": 0
            },
            {
                "id": "100038490645044",
                "count": 0
            },
            {
                "id": "100045760656023",
                "count": 0
            },
            {
                "id": "100006360090592",
                "count": 0
            },
            {
                "id": "100093693425026",
                "count": 0
            },
            {
                "id": "100054130774624",
                "count": 0
            },
            {
                "id": "100080716627589",
                "count": 0
            },
            {
                "id": "100081040767318",
                "count": 0
            },
            {
                "id": "100015636996669",
                "count": 0
            },
            {
                "id": "100047808826017",
                "count": 0
            },
            {
                "id": "100072164630652",
                "count": 0
            },
            {
                "id": "100060569773923",
                "count": 0
            }
        ],
        "week": [
            {
                "id": "100005399974808",
                "count": 0
            },
            {
                "id": "100010295341625",
                "count": 0
            },
            {
                "id": "100048975223261",
                "count": 0
            },
            {
                "id": "100010872618953",
                "count": 0
            },
            {
                "id": "100057840206964",
                "count": 0
            },
            {
                "id": "100010851456335",
                "count": 0
            },
            {
                "id": "100000376441471",
                "count": 0
            },
            {
                "id": "100024680241094",
                "count": 0
            },
            {
                "id": "100008519718621",
                "count": 0
            },
            {
                "id": "100007828906989",
                "count": 0
            },
            {
                "id": "100025965308353",
                "count": 0
            },
            {
                "id": "100001098455658",
                "count": 0
            },
            {
                "id": "100031133040032",
                "count": 0
            },
            {
                "id": "100038141927576",
                "count": 0
            },
            {
                "id": "100053513322881",
                "count": 0
            },
            {
                "id": "100027669353138",
                "count": 0
            },
            {
                "id": "100055755865162",
                "count": 0
            },
            {
                "id": "100017983382767",
                "count": 0
            },
            {
                "id": "100036231517888",
                "count": 0
            },
            {
                "id": "100046802320850",
                "count": 0
            },
            {
                "id": "100048816348048",
                "count": 0
            },
            {
                "id": "100078714226384",
                "count": 0
            },
            {
                "id": "100004112948229",
                "count": 0
            },
            {
                "id": "100088154556576",
                "count": 0
            },
            {
                "id": "100027266034157",
                "count": 0
            },
            {
                "id": "100089855538797",
                "count": 0
            },
            {
                "id": "100021900640152",
                "count": 0
            },
            {
                "id": "100007023435812",
                "count": 0
            },
            {
                "id": "100010074694749",
                "count": 0
            },
            {
                "id": "100010343984032",
                "count": 0
            },
            {
                "id": "100030593837339",
                "count": 0
            },
            {
                "id": "100030127763775",
                "count": 0
            },
            {
                "id": "100034086345546",
                "count": 0
            },
            {
                "id": "100040164439697",
                "count": 0
            },
            {
                "id": "100022367776188",
                "count": 0
            },
            {
                "id": "100008745676374",
                "count": 0
            },
            {
                "id": "100077691835671",
                "count": 0
            },
            {
                "id": "100056381440220",
                "count": 0
            },
            {
                "id": "100044648675640",
                "count": 0
            },
            {
                "id": "100057313594162",
                "count": 0
            },
            {
                "id": "100005071237632",
                "count": 0
            },
            {
                "id": "100074010341361",
                "count": 0
            },
            {
                "id": "100025697650899",
                "count": 0
            },
            {
                "id": "100056376864986",
                "count": 0
            },
            {
                "id": "100008203004097",
                "count": 0
            },
            {
                "id": "100051560712743",
                "count": 0
            },
            {
                "id": "100034658161598",
                "count": 0
            },
            {
                "id": "100009492519807",
                "count": 0
            },
            {
                "id": "100080742369075",
                "count": 0
            },
            {
                "id": "100090006483826",
                "count": 0
            },
            {
                "id": "100090936052047",
                "count": 0
            },
            {
                "id": "100065181827875",
                "count": 0
            },
            {
                "id": "100052380679382",
                "count": 0
            },
            {
                "id": "100073731191766",
                "count": 0
            },
            {
                "id": "100084495626712",
                "count": 0
            },
            {
                "id": "100077313395792",
                "count": 0
            },
            {
                "id": "100034233130232",
                "count": 0
            },
            {
                "id": "100041623599528",
                "count": 0
            },
            {
                "id": "100051694850870",
                "count": 0
            },
            {
                "id": "100039628178101",
                "count": 0
            },
            {
                "id": "100073660227322",
                "count": 0
            },
            {
                "id": "100009167177495",
                "count": 0
            },
            {
                "id": "100025466683106",
                "count": 0
            },
            {
                "id": "100077070300551",
                "count": 0
            },
            {
                "id": "100007359612039",
                "count": 0
            },
            {
                "id": "100034383213099",
                "count": 0
            },
            {
                "id": "100014540290454",
                "count": 0
            },
            {
                "id": "100048561292978",
                "count": 0
            },
            {
                "id": "100031566042722",
                "count": 0
            },
            {
                "id": "100014830098397",
                "count": 0
            },
            {
                "id": "100015473404117",
                "count": 0
            },
            {
                "id": "100040551379448",
                "count": 0
            },
            {
                "id": "100057378228327",
                "count": 0
            },
            {
                "id": "100010294295881",
                "count": 0
            },
            {
                "id": "100069463914769",
                "count": 0
            },
            {
                "id": "100063260620465",
                "count": 0
            },
            {
                "id": "100043601286252",
                "count": 0
            },
            {
                "id": "100044191598642",
                "count": 0
            },
            {
                "id": "100015054305521",
                "count": 0
            },
            {
                "id": "100052419605370",
                "count": 0
            },
            {
                "id": "100041219531906",
                "count": 0
            },
            {
                "id": "100089124229991",
                "count": 0
            },
            {
                "id": "100018064162732",
                "count": 0
            },
            {
                "id": "100013705600597",
                "count": 0
            },
            {
                "id": "100090572663819",
                "count": 0
            },
            {
                "id": "100026450419902",
                "count": 0
            },
            {
                "id": "100034837787551",
                "count": 0
            },
            {
                "id": "100009461997276",
                "count": 0
            },
            {
                "id": "100048432905426",
                "count": 0
            },
            {
                "id": "100067122755501",
                "count": 0
            },
            {
                "id": "100074753293482",
                "count": 0
            },
            {
                "id": "100078786724982",
                "count": 0
            },
            {
                "id": "100079196630165",
                "count": 0
            },
            {
                "id": "100013815225154",
                "count": 0
            },
            {
                "id": "100089488084535",
                "count": 0
            },
            {
                "id": "100053483708297",
                "count": 0
            },
            {
                "id": "100058486843373",
                "count": 0
            },
            {
                "id": "100069400449963",
                "count": 0
            },
            {
                "id": "100055632586900",
                "count": 0
            },
            {
                "id": "100085149474363",
                "count": 0
            },
            {
                "id": "100087707807880",
                "count": 0
            },
            {
                "id": "100042797796681",
                "count": 0
            },
            {
                "id": "100066014461303",
                "count": 0
            },
            {
                "id": "100061314142011",
                "count": 0
            },
            {
                "id": "100015582406225",
                "count": 0
            },
            {
                "id": "100084390475850",
                "count": 0
            },
            {
                "id": "100026107429011",
                "count": 0
            },
            {
                "id": "100015326372925",
                "count": 0
            },
            {
                "id": "100027370416302",
                "count": 0
            },
            {
                "id": "100073925087201",
                "count": 0
            },
            {
                "id": "100037711232386",
                "count": 0
            },
            {
                "id": "100047213045916",
                "count": 0
            },
            {
                "id": "100040224006883",
                "count": 0
            },
            {
                "id": "100015077025240",
                "count": 0
            },
            {
                "id": "100027056261626",
                "count": 0
            },
            {
                "id": "100007158796596",
                "count": 0
            },
            {
                "id": "100064217914106",
                "count": 0
            },
            {
                "id": "100091363366578",
                "count": 0
            },
            {
                "id": "100073204690500",
                "count": 0
            },
            {
                "id": "100008788001367",
                "count": 0
            },
            {
                "id": "100050956162561",
                "count": 0
            },
            {
                "id": "100071393430394",
                "count": 0
            },
            {
                "id": "100047887366084",
                "count": 0
            },
            {
                "id": "100024300976662",
                "count": 0
            },
            {
                "id": "100071636576099",
                "count": 0
            },
            {
                "id": "100041668570533",
                "count": 0
            },
            {
                "id": "100017620472036",
                "count": 0
            },
            {
                "id": "100051807037752",
                "count": 0
            },
            {
                "id": "100008059066610",
                "count": 0
            },
            {
                "id": "100053395998035",
                "count": 0
            },
            {
                "id": "61551446518489",
                "count": 0
            },
            {
                "id": "100073512553764",
                "count": 0
            },
            {
                "id": "100035973543807",
                "count": 0
            },
            {
                "id": "100091344458469",
                "count": 0
            },
            {
                "id": "100085486856463",
                "count": 0
            },
            {
                "id": "100027952612936",
                "count": 0
            },
            {
                "id": "100078216607891",
                "count": 0
            },
            {
                "id": "100017336831405",
                "count": 0
            },
            {
                "id": "100016591539468",
                "count": 0
            },
            {
                "id": "100094469166856",
                "count": 0
            },
            {
                "id": "100044501018946",
                "count": 0
            },
            {
                "id": "100056259933554",
                "count": 0
            },
            {
                "id": "100014343060086",
                "count": 0
            },
            {
                "id": "100077193343212",
                "count": 0
            },
            {
                "id": "100053779121174",
                "count": 0
            },
            {
                "id": "100048884326910",
                "count": 0
            },
            {
                "id": "100027039516065",
                "count": 0
            },
            {
                "id": "100064901298185",
                "count": 0
            },
            {
                "id": "100064573285150",
                "count": 0
            },
            {
                "id": "100047504554005",
                "count": 0
            },
            {
                "id": "100026957449851",
                "count": 0
            },
            {
                "id": "100047221725996",
                "count": 0
            },
            {
                "id": "100054638868722",
                "count": 0
            },
            {
                "id": "100041990565923",
                "count": 0
            },
            {
                "id": "61550226386641",
                "count": 0
            },
            {
                "id": "61551799898681",
                "count": 0
            },
            {
                "id": "100051786424251",
                "count": 0
            },
            {
                "id": "100023128592547",
                "count": 0
            },
            {
                "id": "100006474958727",
                "count": 0
            },
            {
                "id": "61552015658303",
                "count": 0
            },
            {
                "id": "100036921758223",
                "count": 0
            },
            {
                "id": "100089699576670",
                "count": 0
            },
            {
                "id": "100031003510300",
                "count": 0
            },
            {
                "id": "100038490645044",
                "count": 0
            },
            {
                "id": "100045760656023",
                "count": 0
            },
            {
                "id": "100006360090592",
                "count": 0
            },
            {
                "id": "100093693425026",
                "count": 0
            },
            {
                "id": "100054130774624",
                "count": 0
            },
            {
                "id": "100080716627589",
                "count": 0
            },
            {
                "id": "100081040767318",
                "count": 0
            },
            {
                "id": "100015636996669",
                "count": 0
            },
            {
                "id": "100047808826017",
                "count": 0
            },
            {
                "id": "100072164630652",
                "count": 0
            },
            {
                "id": "100060569773923",
                "count": 0
            }
        ]
    }
}